odoo/addons/account_invoice_ubl/README.rst
odoo/addons/account_invoice_ubl/__init__.py
odoo/addons/account_invoice_ubl/__manifest__.py
odoo/addons/account_invoice_ubl/post_install.py
odoo/addons/account_invoice_ubl/i18n/account_invoice_ubl.pot
odoo/addons/account_invoice_ubl/i18n/es.po
odoo/addons/account_invoice_ubl/i18n/fr.po
odoo/addons/account_invoice_ubl/i18n/nl_NL.po
odoo/addons/account_invoice_ubl/models/__init__.py
odoo/addons/account_invoice_ubl/models/account_invoice.py
odoo/addons/account_invoice_ubl/models/ir_actions_report.py
odoo/addons/account_invoice_ubl/models/res_company.py
odoo/addons/account_invoice_ubl/models/res_config_settings.py
odoo/addons/account_invoice_ubl/readme/CONFIGURE.rst
odoo/addons/account_invoice_ubl/readme/CONTRIBUTORS.rst
odoo/addons/account_invoice_ubl/readme/DESCRIPTION.rst
odoo/addons/account_invoice_ubl/static/description/icon.png
odoo/addons/account_invoice_ubl/static/description/index.html
odoo/addons/account_invoice_ubl/tests/__init__.py
odoo/addons/account_invoice_ubl/tests/test_ubl_generate.py
odoo/addons/account_invoice_ubl/views/account_invoice.xml
odoo/addons/account_invoice_ubl/views/res_config_settings.xml
odoo11_addon_account_invoice_ubl-11.0.1.0.1.dist-info/METADATA
odoo11_addon_account_invoice_ubl-11.0.1.0.1.dist-info/WHEEL
odoo11_addon_account_invoice_ubl-11.0.1.0.1.dist-info/top_level.txt
odoo11_addon_account_invoice_ubl-11.0.1.0.1.dist-info/RECORD
